interlinears/__init__.py
interlinears/leipzig.py
interlinears-0.3.dist-info/WHEEL
interlinears-0.3.dist-info/METADATA
interlinears-0.3.dist-info/RECORD
